{
    "BaseSpeed": 76,
    "HiddenAbility": "せいしんりょく",
    "BaseHP": 50,
    "EggGroups": [
        "人型"
    ],
    "BaseSpDef": 110,
    "BaseAtk": 105,
    "BaseSpAtk": 35,
    "Weight": 50.2,
    "Types": [
        "かくとう"
    ],
    "Height": 1.4,
    "Learnset": [
        "ドレインパンチ",
        "フェイント",
        "しんくうは",
        "バレットパンチ",
        "たいあたり",
        "てだすけ",
        "ねこだまし",
        "きあいだめ",
        "マッハパンチ",
        "グロウパンチ",
        "みきり",
        "リベンジ",
        "ファストガード",
        "かみなりパンチ",
        "れいとうパンチ",
        "ほのおのパンチ",
        "こうそくいどう",
        "メガトンパンチ",
        "インファイト",
        "カウンター",
        "きあいパンチ",
        "メガトンキック",
        "ねむる",
        "いわなだれ",
        "どろぼう",
        "いびき",
        "まもる",
        "メロメロ",
        "あまごい",
        "にほんばれ",
        "からげんき",
        "スピードスター",
        "かわらわり",
        "がんせきふうじ",
        "なげつける",
        "ローキック",
        "りんしょう",
        "かたきうち",
        "じならし",
        "のしかかり",
        "けたぐり",
        "じしん",
        "ゆびをふる",
        "みがわり",
        "こらえる",
        "ねごと",
        "さわぐ",
        "ビルドアップ",
        "はどうだん",
        "きあいだま",
        "ストーンエッジ",
        "ふるいたてる",
        "じごくづき",
        "とびひざげり",
        "こころのめ",
        "こうそくスピン",
        "コーチング"
    ],
    "NormalAbilities": [
        "するどいめ",
        "てつのこぶし"
    ],
    "AllAbilities": [
        "するどいめ",
        "てつのこぶし",
        "せいしんりょく"
    ],
    "Category": "通常ポケモン",
    "Gender": "♂のみ",
    "BaseDef": 79
}