{
    "BaseSpeed": 71,
    "HiddenAbility": "いしあたま",
    "BaseHP": 82,
    "EggGroups": [
        "怪獣",
        "ドラゴン"
    ],
    "BaseSpDef": 59,
    "BaseAtk": 121,
    "BaseSpAtk": 69,
    "Weight": 270.0,
    "Types": [
        "いわ",
        "ドラゴン"
    ],
    "Height": 2.5,
    "Learnset": [
        "しっぽをふる",
        "たいあたり",
        "ほえる",
        "げんしのちから",
        "あまえる",
        "かみつく",
        "ドラゴンテール",
        "ふみつけ",
        "いわなだれ",
        "かみくだく",
        "ドラゴンクロー",
        "あばれる",
        "じしん",
        "つのドリル",
        "ギガインパクト",
        "もろはのずつき",
        "はかいこうせん",
        "あなをほる",
        "ねむる",
        "いびき",
        "まもる",
        "こわいかお",
        "メロメロ",
        "すなあらし",
        "にほんばれ",
        "からげんき",
        "かわらわり",
        "がんせきふうじ",
        "ロックブラスト",
        "ダメおし",
        "かみなりのキバ",
        "こおりのキバ",
        "ほのおのキバ",
        "りんしょう",
        "じならし",
        "ぶんまわす",
        "じだんだ",
        "ワイドブレイカー",
        "のしかかり",
        "みがわり",
        "げきりん",
        "こらえる",
        "ねごと",
        "アイアンテール",
        "ばかぢから",
        "ハイパーボイス",
        "てっぺき",
        "りゅうのまい",
        "インファイト",
        "あくのはどう",
        "りゅうのはどう",
        "だいちのちから",
        "しねんのずつき",
        "アイアンヘッド",
        "ストーンエッジ",
        "ステルスロック",
        "じゃれつく",
        "10まんばりき",
        "サイコファング",
        "いわおとし",
        "のろい",
        "どくどくのキバ",
        "ロックカット",
        "スケイルショット",
        "メテオビーム",
        "うっぷんばらし",
        "りゅうせいぐん"
    ],
    "NormalAbilities": [
        "がんじょうあご"
    ],
    "AllAbilities": [
        "がんじょうあご",
        "いしあたま"
    ],
    "Category": "通常ポケモン",
    "Gender": "♂♀両方",
    "BaseDef": 119
}