{
    "BaseSpeed": 90,
    "HiddenAbility": "テレパシー",
    "BaseHP": 60,
    "EggGroups": [
        "虫"
    ],
    "BaseSpDef": 120,
    "BaseAtk": 45,
    "BaseSpAtk": 80,
    "Weight": 40.8,
    "Types": [
        "むし",
        "エスパー"
    ],
    "Height": 0.4,
    "Learnset": [
        "リフレクター",
        "ひかりのかべ",
        "ねんりき",
        "むしのていこう",
        "あやしいひかり",
        "マジックコート",
        "こうそくいどう",
        "サイケこうせん",
        "さいみんじゅつ",
        "サイドチェンジ",
        "むしのさざめき",
        "ミラーコート",
        "サイコキネシス",
        "おさきにどうぞ",
        "めいそう",
        "サイコフィールド",
        "はかいこうせん",
        "ギガインパクト",
        "ソーラービーム",
        "しんぴのまもり",
        "ねむる",
        "いびき",
        "まもる",
        "ギガドレイン",
        "メロメロ",
        "からげんき",
        "てだすけ",
        "ふういん",
        "とんぼがえり",
        "しっぺがえし",
        "パワースワップ",
        "ガードスワップ",
        "サイコカッター",
        "トリックルーム",
        "ワンダールーム",
        "マジックルーム",
        "りんしょう",
        "きゅうけつ",
        "みがわり",
        "サイコショック",
        "こらえる",
        "ねごと",
        "バトンタッチ",
        "シャドーボール",
        "みらいよち",
        "トリック",
        "スキルスワップ",
        "てっぺき",
        "エナジーボール",
        "しねんのずつき",
        "アシストパワー",
        "ボディプレス",
        "ちょうおんぱ",
        "じこさいせい",
        "まとわりつく",
        "ねばねばネット",
        "ワイドフォース"
    ],
    "NormalAbilities": [
        "むしのしらせ",
        "おみとおし"
    ],
    "AllAbilities": [
        "むしのしらせ",
        "おみとおし",
        "テレパシー"
    ],
    "Category": "通常ポケモン",
    "Gender": "♂♀両方",
    "BaseDef": 110
}