{
    "BaseSpeed": 85,
    "HiddenAbility": "なし",
    "BaseHP": 70,
    "EggGroups": [
        "水中1",
        "飛行"
    ],
    "BaseSpDef": 95,
    "BaseAtk": 85,
    "BaseSpAtk": 85,
    "Weight": 18.0,
    "Types": [
        "ひこう",
        "みず"
    ],
    "Height": 0.8,
    "Learnset": [
        "ゲップ",
        "つつく",
        "たくわえる",
        "のみこむ",
        "はきだす",
        "みずでっぽう",
        "みだれづき",
        "ついばむ",
        "ダイビング",
        "ドリルくちばし",
        "ドわすれ",
        "あばれる",
        "ハイドロポンプ",
        "そらをとぶ",
        "はかいこうせん",
        "ギガインパクト",
        "ねむる",
        "どろぼう",
        "いびき",
        "まもる",
        "こごえるかぜ",
        "はがねのつばさ",
        "メロメロ",
        "あまごい",
        "うずしお",
        "からげんき",
        "ウェザーボール",
        "ダメおし",
        "りんしょう",
        "エアスラッシュ",
        "なみのり",
        "れいとうビーム",
        "ふぶき",
        "こうそくいどう",
        "みがわり",
        "きしかいせい",
        "こらえる",
        "ねごと",
        "さわぐ",
        "ばかぢから",
        "ブレイブバード",
        "ねっとう",
        "ぼうふう",
        "じごくづき",
        "アクアブレイク",
        "フェザーダンス",
        "つばめがえし",
        "はねやすめ",
        "アクアリング",
        "きりばらい",
        "ダブルウイング"
    ],
    "NormalAbilities": [
        "うのミサイル"
    ],
    "AllAbilities": [
        "うのミサイル"
    ],
    "Category": "通常ポケモン",
    "Gender": "♂♀両方",
    "BaseDef": 55
}