{
    "BaseSpeed": 160,
    "HiddenAbility": "すりぬけ",
    "BaseHP": 61,
    "EggGroups": [
        "虫"
    ],
    "BaseSpDef": 50,
    "BaseAtk": 90,
    "BaseSpAtk": 50,
    "Weight": 12.0,
    "Types": [
        "むし",
        "ひこう"
    ],
    "Height": 0.8,
    "Learnset": [
        "かげぶんしん",
        "いやなおと",
        "れんぞくぎり",
        "ひっかく",
        "かたくなる",
        "すなかけ",
        "バトンタッチ",
        "つばめがえし",
        "どろかけ",
        "メタルクロー",
        "あなをほる",
        "みねうち",
        "こうそくいどう",
        "すいとる",
        "むしくい",
        "みだれひっかき",
        "こころのめ",
        "きりさく",
        "つるぎのまい",
        "シザークロス",
        "はかいこうせん",
        "ギガインパクト",
        "ソーラービーム",
        "ねむる",
        "どろぼう",
        "いびき",
        "まもる",
        "ギガドレイン",
        "すなあらし",
        "にほんばれ",
        "からげんき",
        "スピードスター",
        "とんぼがえり",
        "りんしょう",
        "アクロバット",
        "エアスラッシュ",
        "きゅうけつ",
        "みがわり",
        "こらえる",
        "ねごと",
        "シャドーボール",
        "さわぐ",
        "むしのさざめき",
        "かぜおこし",
        "じたばた",
        "つじぎり",
        "いのちがけ",
        "はいよるいちげき",
        "ダブルウイング"
    ],
    "NormalAbilities": [
        "かそく"
    ],
    "AllAbilities": [
        "かそく",
        "すりぬけ"
    ],
    "Category": "通常ポケモン",
    "Gender": "♂♀両方",
    "BaseDef": 45
}