{
    "BaseSpeed": 30,
    "HiddenAbility": "なし",
    "BaseHP": 58,
    "EggGroups": [
        "鉱物",
        "不定形"
    ],
    "BaseSpDef": 105,
    "BaseAtk": 50,
    "BaseSpAtk": 95,
    "Weight": 76.5,
    "Types": [
        "ゴースト"
    ],
    "Height": 1.7,
    "Learnset": [
        "シャドークロー",
        "おどろかす",
        "まもる",
        "くろいきり",
        "こわいかお",
        "ナイトヘッド",
        "かなしばり",
        "おにび",
        "トリックガード",
        "たたりめ",
        "くろいまなざし",
        "おんねん",
        "のろい",
        "シャドーボール",
        "あくのはどう",
        "パワーシェア",
        "ガードシェア",
        "みちづれ",
        "はかいこうせん",
        "ギガインパクト",
        "しんぴのまもり",
        "ねむる",
        "どろぼう",
        "いびき",
        "メロメロ",
        "あまごい",
        "からげんき",
        "リベンジ",
        "ふういん",
        "うそなき",
        "しっぺがえし",
        "パワースワップ",
        "ガードスワップ",
        "トリックルーム",
        "ワンダールーム",
        "りんしょう",
        "ゴーストダイブ",
        "サイコキネシス",
        "みがわり",
        "こらえる",
        "ねごと",
        "トリック",
        "スキルスワップ",
        "てっぺき",
        "めいそう",
        "どくびし",
        "エナジーボール",
        "わるだくみ",
        "しねんのずつき",
        "くさむすび",
        "サイドチェンジ",
        "ボディプレス",
        "おきみやげ",
        "ポルターガイスト"
    ],
    "NormalAbilities": [
        "ミイラ"
    ],
    "AllAbilities": [
        "ミイラ"
    ],
    "Category": "通常ポケモン",
    "Gender": "♂♀両方",
    "BaseDef": 145
}