{
    "BaseSpeed": 40,
    "HiddenAbility": "すてみ",
    "BaseHP": 115,
    "EggGroups": [
        "怪獣",
        "陸上"
    ],
    "BaseSpDef": 55,
    "BaseAtk": 140,
    "BaseSpAtk": 55,
    "Weight": 282.8,
    "Types": [
        "じめん",
        "いわ"
    ],
    "Height": 2.4,
    "Learnset": [
        "しっぽをふる",
        "アームハンマー",
        "たいあたり",
        "うちおとす",
        "じならし",
        "つのでつく",
        "こわいかお",
        "ふみつけ",
        "ロックブラスト",
        "ドリルライナー",
        "とっしん",
        "じしん",
        "ストーンエッジ",
        "メガホーン",
        "つのドリル",
        "がんせきほう",
        "メガトンパンチ",
        "メガトンキック",
        "ネコにこばん",
        "ほのおのパンチ",
        "れいとうパンチ",
        "かみなりパンチ",
        "はかいこうせん",
        "ギガインパクト",
        "あなをほる",
        "ねむる",
        "いわなだれ",
        "どろぼう",
        "いびき",
        "まもる",
        "こごえるかぜ",
        "メロメロ",
        "すなあらし",
        "あまごい",
        "にほんばれ",
        "うずしお",
        "からげんき",
        "てだすけ",
        "かわらわり",
        "がんせきふうじ",
        "マッドショット",
        "しっぺがえし",
        "なげつける",
        "ゆきなだれ",
        "シャドークロー",
        "かみなりのキバ",
        "こおりのキバ",
        "ほのおのキバ",
        "りんしょう",
        "スマートホーン",
        "ぶんまわす",
        "じだんだ",
        "ワイドブレイカー",
        "つるぎのまい",
        "のしかかり",
        "かえんほうしゃ",
        "ハイドロポンプ",
        "なみのり",
        "れいとうビーム",
        "ふぶき",
        "10まんボルト",
        "かみなり",
        "だいもんじ",
        "みがわり",
        "きしかいせい",
        "げきりん",
        "こらえる",
        "ねごと",
        "アイアンテール",
        "かみくだく",
        "さわぐ",
        "ばかぢから",
        "てっぺき",
        "どくづき",
        "りゅうのはどう",
        "きあいだま",
        "だいちのちから",
        "ラスターカノン",
        "アイアンヘッド",
        "ステルスロック",
        "ヘビーボンバー",
        "ヒートスタンプ",
        "10まんばりき",
        "ボディプレス",
        "カウンター",
        "ロケットずつき",
        "のろい",
        "メタルバースト",
        "ロックカット",
        "ドラゴンダイブ",
        "ガードシェア",
        "メテオビーム",
        "ねっさのだいち"
    ],
    "NormalAbilities": [
        "ひらいしん",
        "ハードロック"
    ],
    "AllAbilities": [
        "ひらいしん",
        "ハードロック",
        "すてみ"
    ],
    "Category": "通常ポケモン",
    "Gender": "♂♀両方",
    "BaseDef": 130
}