{
    "BaseSpeed": 45,
    "HiddenAbility": "さいせいりょく",
    "BaseHP": 50,
    "EggGroups": [
        "水中1"
    ],
    "BaseSpDef": 52,
    "BaseAtk": 53,
    "BaseSpAtk": 43,
    "Weight": 8.0,
    "Types": [
        "どく",
        "みず"
    ],
    "Height": 0.4,
    "Learnset": [
        "どくばり",
        "つつく",
        "ワイドガード",
        "かみつく",
        "ベノムショック",
        "じこさいせい",
        "ミサイルばり",
        "どくびし",
        "アクアブレイク",
        "ベノムトラップ",
        "どくづき",
        "どくどく",
        "しんぴのまもり",
        "ねむる",
        "いびき",
        "まもる",
        "こごえるかぜ",
        "メロメロ",
        "あまごい",
        "あられ",
        "からげんき",
        "マッドショット",
        "しおみず",
        "しっぺがえし",
        "りんしょう",
        "ハイドロポンプ",
        "なみのり",
        "れいとうビーム",
        "ふぶき",
        "みがわり",
        "ヘドロばくだん",
        "こらえる",
        "ねごと",
        "だくりゅう",
        "てっぺき",
        "ダストシュート",
        "ヘドロウェーブ",
        "ねっとう",
        "くろいきり",
        "たくわえる",
        "はきだす",
        "のみこむ",
        "まとわりつく"
    ],
    "NormalAbilities": [
        "ひとでなし",
        "じゅうなん"
    ],
    "AllAbilities": [
        "ひとでなし",
        "じゅうなん",
        "さいせいりょく"
    ],
    "Category": "通常ポケモン",
    "Gender": "♂♀両方",
    "BaseDef": 62
}