{
    "BaseSpeed": 30,
    "HiddenAbility": "アナライズ",
    "BaseHP": 55,
    "EggGroups": [
        "人型"
    ],
    "BaseSpDef": 55,
    "BaseAtk": 55,
    "BaseSpAtk": 85,
    "Weight": 9.0,
    "Types": [
        "エスパー"
    ],
    "Height": 0.5,
    "Learnset": [
        "ねんりき",
        "なきごえ",
        "ふういん",
        "テレポート",
        "サイケこうせん",
        "パワーシェア",
        "ガードシェア",
        "ずつき",
        "しねんのずつき",
        "じこさいせい",
        "めいそう",
        "ワンダールーム",
        "サイコキネシス",
        "でんじは",
        "いやなおと",
        "ひかりのかべ",
        "リフレクター",
        "しんぴのまもり",
        "ねむる",
        "いわなだれ",
        "どろぼう",
        "いびき",
        "まもる",
        "はがねのつばさ",
        "メロメロ",
        "あまごい",
        "からげんき",
        "がんせきふうじ",
        "パワースワップ",
        "ガードスワップ",
        "トリックルーム",
        "りんしょう",
        "10まんボルト",
        "こうそくいどう",
        "みがわり",
        "サイコショック",
        "こらえる",
        "ねごと",
        "シャドーボール",
        "さわぐ",
        "トリック",
        "スキルスワップ",
        "コスモパワー",
        "あくのはどう",
        "エナジーボール",
        "わるだくみ",
        "アシストパワー",
        "サイドチェンジ",
        "かなしばり",
        "みちづれ",
        "じこあんじ",
        "おどろかす",
        "ワイドフォース",
        "メテオビーム"
    ],
    "NormalAbilities": [
        "テレパシー",
        "シンクロ"
    ],
    "AllAbilities": [
        "テレパシー",
        "シンクロ",
        "アナライズ"
    ],
    "Category": "通常ポケモン",
    "Gender": "♂♀両方",
    "BaseDef": 55
}